sapiens_tokenizer/__init__.py
sapiens_tokenizer/sapiens_tokenizer.py
sapiens_tokenizer/vocabulary.json
sapiens_tokenizer-1.2.3.dist-info/LICENSE.txt
sapiens_tokenizer-1.2.3.dist-info/METADATA
sapiens_tokenizer-1.2.3.dist-info/WHEEL
sapiens_tokenizer-1.2.3.dist-info/top_level.txt
sapiens_tokenizer-1.2.3.dist-info/RECORD
