Metadata-Version: 2.2
Name: sapiens_tokenizer
Version: 1.2.3
Home-page: https://github.com/sapiens-technology/SapiensTokenizer
Author: SAPIENS TECHNOLOGY
License: Proprietary Software
License-File: LICENSE.txt
Requires-Dist: tiktoken
Requires-Dist: certifi
Dynamic: author
Dynamic: home-page
Dynamic: license
Dynamic: requires-dist
